pywintunx_pmd3.cp311-win_amd64.pyd
wintun_driver/__init__.py
wintun_driver/__main__.py
pywintunx_pmd3-1.0.2.dist-info/COPYING
pywintunx_pmd3-1.0.2.dist-info/METADATA
pywintunx_pmd3-1.0.2.dist-info/WHEEL
pywintunx_pmd3-1.0.2.dist-info/top_level.txt
pywintunx_pmd3-1.0.2.dist-info/RECORD
