Metadata-Version: 2.1
Name: pywintunx-pmd3
Version: 1.0.2
Summary: wintun (WireGuard) wrapper for Python
Home-page: https://github.com/unknown/wintun
Author: unknown
Author-email: unknown@gmail.com
Maintainer: unknown
Maintainer-email: unknown@gmail.com
Classifier: Development Status :: 5 - Production/Stable
Classifier: Intended Audience :: Developers
Classifier: License :: OSI Approved :: MIT License
Classifier: Operating System :: Microsoft :: Windows
Classifier: Programming Language :: C
Classifier: Programming Language :: Python :: 2
Classifier: Programming Language :: Python :: 3
Classifier: Topic :: Software Development :: Libraries :: Python Modules
Classifier: Topic :: System :: Networking
Requires: click
Requires: pyuac
License-File: COPYING
